neops_workflow_engine_client/__init__.py
neops_workflow_engine_client/api/__init__.py
neops_workflow_engine_client/api/blackboard_api.py
neops_workflow_engine_client/api/cms_client_api.py
neops_workflow_engine_client/api/default_api.py
neops_workflow_engine_client/api/function_block_api.py
neops_workflow_engine_client/api/health_api.py
neops_workflow_engine_client/api/workflows_api.py
neops_workflow_engine_client/api_client.py
neops_workflow_engine_client/api_response.py
neops_workflow_engine_client/configuration.py
neops_workflow_engine_client/exceptions.py
neops_workflow_engine_client/models/__init__.py
neops_workflow_engine_client/models/acquires.py
neops_workflow_engine_client/models/create_workflow_definition_dto.py
neops_workflow_engine_client/models/cron_configuration.py
neops_workflow_engine_client/models/crontab_configuration.py
neops_workflow_engine_client/models/device_dto.py
neops_workflow_engine_client/models/devices_response_dto.py
neops_workflow_engine_client/models/execute_workflow_dto.py
neops_workflow_engine_client/models/health_response.py
neops_workflow_engine_client/models/job_definition_dto.py
neops_workflow_engine_client/models/job_result_dto.py
neops_workflow_engine_client/models/login_response_dto.py
neops_workflow_engine_client/models/parametrized_function_block.py
neops_workflow_engine_client/models/register_function_block_dto.py
neops_workflow_engine_client/models/repeat_configuration.py
neops_workflow_engine_client/models/retry_configuration.py
neops_workflow_engine_client/models/root_workflow.py
neops_workflow_engine_client/models/workflow.py
neops_workflow_engine_client/models/workflow_config.py
neops_workflow_engine_client/models/workflow_execution_parameters.py
neops_workflow_engine_client/models/workflow_reference.py
neops_workflow_engine_client/models/workflow_steps_inner.py
neops_workflow_engine_client/py.typed
neops_workflow_engine_client/rest.py
neops_workflow_engine_client-0.41.10.dist-info/METADATA
neops_workflow_engine_client-0.41.10.dist-info/WHEEL
neops_workflow_engine_client-0.41.10.dist-info/RECORD
